<annotation><folder>images</folder><filename>egfr_M_R_oly_2X_58.jpg</filename><path>/home/hoangnm/dataset2/data/egfr_M_R_oly_2X_58.jpg</path><source><database>unknowned</database></source><size><width>1024</width><height>1360</height><depth>3</depth></size><segment>0</segment><object><name>0</name><pose>Unspecified</pose><truncated>0</truncated><difficult>0</difficult><bndbox><xmin>529</xmin><ymin>649</ymin><xmax>559</xmax><ymax>679</ymax></bndbox></object><object><name>1</name><pose>Unspecified</pose><truncated>0</truncated><difficult>0</difficult><bndbox><xmin>566</xmin><ymin>577</ymin><xmax>596</xmax><ymax>607</ymax></bndbox></object><object><name>2</name><pose>Unspecified</pose><truncated>0</truncated><difficult>0</difficult><bndbox><xmin>493</xmin><ymin>602</ymin><xmax>523</xmax><ymax>632</ymax></bndbox></object><object><name>3</name><pose>Unspecified</pose><truncated>0</truncated><difficult>0</difficult><bndbox><xmin>438</xmin><ymin>622</ymin><xmax>468</xmax><ymax>652</ymax></bndbox></object><object><name>4</name><pose>Unspecified</pose><truncated>0</truncated><difficult>0</difficult><bndbox><xmin>439</xmin><ymin>552</ymin><xmax>469</xmax><ymax>582</ymax></bndbox></object><object><name>5</name><pose>Unspecified</pose><truncated>0</truncated><difficult>0</difficult><bndbox><xmin>411</xmin><ymin>601</ymin><xmax>441</xmax><ymax>631</ymax></bndbox></object><object><name>6</name><pose>Unspecified</pose><truncated>0</truncated><difficult>0</difficult><bndbox><xmin>967</xmin><ymin>489</ymin><xmax>997</xmax><ymax>519</ymax></bndbox></object><object><name>7</name><pose>Unspecified</pose><truncated>0</truncated><difficult>0</difficult><bndbox><xmin>936</xmin><ymin>433</ymin><xmax>966</xmax><ymax>463</ymax></bndbox></object><object><name>8</name><pose>Unspecified</pose><truncated>0</truncated><difficult>0</difficult><bndbox><xmin>647</xmin><ymin>511</ymin><xmax>677</xmax><ymax>541</ymax></bndbox></object><object><name>9</name><pose>Unspecified</pose><truncated>0</truncated><difficult>0</difficult><bndbox><xmin>454</xmin><ymin>565</ymin><xmax>484</xmax><ymax>595</ymax></bndbox></object><object><name>10</name><pose>Unspecified</pose><truncated>0</truncated><difficult>0</difficult><bndbox><xmin>878</xmin><ymin>609</ymin><xmax>908</xmax><ymax>639</ymax></bndbox></object><object><name>11</name><pose>Unspecified</pose><truncated>0</truncated><difficult>0</difficult><bndbox><xmin>690</xmin><ymin>379</ymin><xmax>720</xmax><ymax>409</ymax></bndbox></object><object><name>12</name><pose>Unspecified</pose><truncated>0</truncated><difficult>0</difficult><bndbox><xmin>427</xmin><ymin>654</ymin><xmax>457</xmax><ymax>684</ymax></bndbox></object><object><name>13</name><pose>Unspecified</pose><truncated>0</truncated><difficult>0</difficult><bndbox><xmin>556</xmin><ymin>560</ymin><xmax>586</xmax><ymax>590</ymax></bndbox></object><object><name>14</name><pose>Unspecified</pose><truncated>0</truncated><difficult>0</difficult><bndbox><xmin>627</xmin><ymin>468</ymin><xmax>657</xmax><ymax>498</ymax></bndbox></object></annotation>